ffmpegaudiorecord/README.MD
ffmpegaudiorecord/__init__.py
ffmpegaudiorecord/requirements.txt
ffmpegaudiorecord/thirdparty.json
ffmpegaudiorecord-0.11.dist-info/LICENSE.rst
ffmpegaudiorecord-0.11.dist-info/METADATA
ffmpegaudiorecord-0.11.dist-info/WHEEL
ffmpegaudiorecord-0.11.dist-info/top_level.txt
ffmpegaudiorecord-0.11.dist-info/RECORD
