Metadata-Version: 2.1
Name: ffmpegaudiorecord
Version: 0.11
Summary: Starts recording audio from the specified device using ffmpeg and stops recording after a specified number of seconds of silence
Home-page: https://github.com/hansalemaos/ffmpegaudiorecord
Author: Johannes Fischer
Author-email: aulasparticularesdealemaosp@gmail.com
License: MIT
Keywords: ffmpeg,audio,record
Classifier: Development Status :: 4 - Beta
Classifier: Programming Language :: Python :: 3 :: Only
Classifier: Programming Language :: Python :: 3.10
Classifier: Topic :: Software Development :: Libraries :: Python Modules
Classifier: Topic :: Utilities
License-File: LICENSE.rst
Requires-Dist: ffmpegdevices
Requires-Dist: kthread
Requires-Dist: pydub
Requires-Dist: subprocess-alive
Requires-Dist: subprocesskiller
